geospatial/__init__.py
geospatial/algorithms/__init__.py
geospatial/algorithms/pathfinding.py
geospatial/algorithms/perception.py
geospatial/core/__init__.py
geospatial/core/exceptions.py
geospatial/core/graph.py
geospatial/core/observer.py
geospatial/entities/__init__.py
geospatial/entities/coordinate.py
geospatial/entities/poi.py
geospatial/entities/road.py
geospatial/io/__init__.py
geospatial/io/geojson_reader.py
geospatial/io/shapefile_reader.py
geospatial/utils/__init__.py
geospatial/utils/distance.py
geospatial/utils/geometry.py
geospatial/visualization/__init__.py
geospatial/visualization/map_visualizer.py
gisense/__init__.py
gisense/algorithms/__init__.py
gisense/algorithms/pathfinding.py
gisense/algorithms/perception.py
gisense/core/__init__.py
gisense/core/exceptions.py
gisense/core/graph.py
gisense/core/observer.py
gisense/entities/__init__.py
gisense/entities/coordinate.py
gisense/entities/poi.py
gisense/entities/road.py
gisense/io/__init__.py
gisense/io/geojson_reader.py
gisense/io/shapefile_reader.py
gisense/utils/__init__.py
gisense/utils/distance.py
gisense/utils/geometry.py
gisense/visualization/__init__.py
gisense/visualization/map_visualizer.py
gisense-0.0.1.dist-info/METADATA
gisense-0.0.1.dist-info/WHEEL
gisense-0.0.1.dist-info/top_level.txt
gisense-0.0.1.dist-info/RECORD
